{
  "caseData": {
    "type": "GrantOfRepresentation",
    "applicationType": "Personal",
    "primaryApplicantEmailAddress": "jsnow@bbc.co.uk",
    "primaryApplicantForenames": "Jon",
    "primaryApplicantSurname": "Snow",
    "primaryApplicantAddress": {
      "AddressLine1": "Pret a Manger",
      "AddressLine2": "St. Georges Hospital",
      "PostTown": "London",
      "PostCode": "SW17 0QT"
    },
    "primaryApplicantFreeTextAddress": "Pret a Manger St. Georges Hospital Blackshaw Road",
    "primaryApplicantAddressFound": "Yes",
    "primaryApplicantPhoneNumber": "123455678",
    "primaryApplicantRelationshipToDeceased": "adoptedChild",
    "primaryApplicantAdoptionInEnglandOrWales": "Yes",
    "deceasedForenames": "Ned",
    "deceasedSurname": "Stark",
    "deceasedDateOfBirth": "1930-01-01",
    "deceasedDateOfDeath": "2018-01-01",
    "deceasedAddress": {
      "AddressLine1": "Winterfell",
      "AddressLine2": " Westeros",
      "PostTown": "London",
      "PostCode": "SW17 0QT"
    },
    "deceasedFreeTextAddress": "Winterfell, Westeros",
    "deceasedAddressFound": "Yes",
    "deceasedAnyOtherNames": "No",
    "deceasedAliasNameList": [
      {
        "value": {
          "Forenames": "Bobby",
          "LastName": "Smith"
        }
      }
    ],
    "deceasedMartialStatus": "marriedCivilPartnership",
    "deceasedDivorcedInEnglandOrWales": "No",
    "deceasedSpouseNotApplyingReason": "mentallyIncapable",
    "deceasedOtherChildren": "Yes",
    "childrenOverEighteenSurvived": "Yes",
    "childrenDied": "No",
    "grandChildrenSurvivedUnderEighteen": "No",
    "deceasedAnyChildren": "No",
    "registryLocation": "Birmingham",
    "assetsOverseasNetValue": "10050",
    "deceasedHasAssetsOutsideUK": "Yes",
    "ihtFormId": "IHT205",
    "ihtFormCompletedOnline": "No",
    "ihtNetValue": "900001",
    "ihtGrossValue": "1000001",
    "ihtReferenceNumber": "Not applicable",
    "willHasCodicils": "No",
    "willNumberOfCodicils": 1,
    "executorsHaveAlias": "Yes",
    "executorsAllAlive": "Yes",
    "otherExecutorsApplying" : "No",
    "numberOfExecutors": 2,
    "executorsApplying": [
      {
        "value": {
          "applyingExecutorName": "Jon Snw",
          "applyingExecutorPhoneNumber": "07981898999",
          "applyingExecutorAgreed": "Yes",
          "applyingExecutorEmail": "address@email.com",
          "applyingExecutorInvitationId": "54321",
          "applyingExecutorLeadName":"Graham Garderner",
          "applyingExecutorAddress": {
            "AddressLine1": "12 West End Avenue",
            "AddressLine2": "St. Georges Hospital",
            "PostTown": "London",
            "PostCode": "SW17 0QT"
          },
          "applyingExecutorOtherNames": "Graham Poll",
          "applyingExecutorOtherNamesReason": "Divorce"
        }
      },
      {
        "value": {
          "applyingExecutorName": "Jackie Smith",
          "applyingExecutorPhoneNumber": "07981898999",
          "applyingExecutorAgreed": "Yes",
          "applyingExecutorEmail": "address@email.com",
          "applyingExecutorInvitationId": "54321",
          "applyingExecutorLeadName":"Graham Garderner",
          "applyingExecutorAddress": {
            "AddressLine1": "12 West End Avenue",
            "AddressLine2": "St. Georges Hospital",
            "PostTown": "London",
            "PostCode": "SW17 0QT"
          },
          "applyingExecutorOtherNames": "Graham Poll",
          "applyingExecutorOtherNamesReason": "Divorce"
        }
      }
    ],
    "executorsNotApplying": [
    ],
    "declarationCheckbox": "Yes",
    "extraCopiesOfGrant": 5,
    "outsideUKGrantCopies": 6,
    "uploadDocumentUrl": "http://document-management/document/12345"
  },
  "caseInfo": {
    "caseId": "12323213323",
    "state": "Draft"
  }
}